panyc.py
panyc-1.0.0.data/scripts/panyc.py
panyc-1.0.0.dist-info/METADATA
panyc-1.0.0.dist-info/WHEEL
panyc-1.0.0.dist-info/top_level.txt
panyc-1.0.0.dist-info/RECORD
