Metadata-Version: 2.4
Name: panyc
Version: 1.0.0
Home-page: https://codeberg.org/bnz/panyc
Author: bnz
Author-email: matteo.benzi97@gmail.com
License: MIT
Dynamic: author
Dynamic: author-email
Dynamic: description
Dynamic: description-content-type
Dynamic: home-page
Dynamic: license
